dumpdork/__init__.py
dumpdork/main.py
dumpdork-0.1.6.dist-info/licenses/LICENSE
dumpdork-0.1.6.dist-info/METADATA
dumpdork-0.1.6.dist-info/WHEEL
dumpdork-0.1.6.dist-info/entry_points.txt
dumpdork-0.1.6.dist-info/top_level.txt
dumpdork-0.1.6.dist-info/RECORD
