Metadata-Version: 2.4
Name: dumpdork
Version: 0.1.6
Summary: A powerful command-line tool for Google dorking, enabling users to uncover hidden information and vulnerabilities with advanced search queries.
Home-page: https://github.com/mateofumis/dumpdork
Author: Mateo Fumis
Author-email: mateofumis1@gmail.com
Classifier: Programming Language :: Python :: 3
Classifier: License :: OSI Approved :: Apache Software License
Classifier: Operating System :: OS Independent
Requires-Python: >=3.6
License-File: LICENSE
Requires-Dist: colorama==0.4.6
Requires-Dist: PyYAML==6.0.1
Requires-Dist: requests==2.32.3
Dynamic: author
Dynamic: author-email
Dynamic: classifier
Dynamic: description
Dynamic: description-content-type
Dynamic: home-page
Dynamic: license-file
Dynamic: requires-dist
Dynamic: requires-python
Dynamic: summary
